psv/__init__.py
psv/load_utils.py
psv/main.py
psv/core/__init__.py
psv/core/exceptions/__init__.py
psv/core/exceptions/messages.py
psv/core/objects/__init__.py
psv/core/objects/apiobjects.py
psv/core/objects/rowobjects.py
psv/core/objects/selections.py
psv/core/output/__init__.py
psv/core/output/main.py
psv/core/parsing/__init__.py
psv/core/parsing/main.py
psv/core/utils/__init__.py
psv/core/utils/main.py
psv/core/utils/objects.py
psv-0.4.1.dist-info/LICENSE.txt
psv-0.4.1.dist-info/METADATA
psv-0.4.1.dist-info/WHEEL
psv-0.4.1.dist-info/top_level.txt
psv-0.4.1.dist-info/RECORD
