Metadata-Version: 2.1
Name: psv
Version: 0.4.1
Summary: CSV Parser
Home-page: https://github.com/DolphDev/PSV
Author: Joshua W
Author-email: DolphDevgithub@gmail.com
Keywords: csv,Comma Separated Values,Python Separated Values,psv
Classifier: License :: OSI Approved :: MIT License
Classifier: Operating System :: OS Independent
Classifier: Topic :: Utilities
Classifier: Programming Language :: Python :: 3.2
Classifier: Programming Language :: Python :: 3.3
Classifier: Programming Language :: Python :: 3.4
Classifier: Programming Language :: Python :: 3.5
Classifier: Programming Language :: Python :: 3.6
License-File: LICENSE.txt
Requires-Dist: tabulate (==0.8.10)
